Workbook

Sheet Dmart_RetailBusiness
A1: order_id | B1: Order_Month | C1: order_date | D1: region | E1: sales | F1: category | G1: discount | H1: quantity | I1: delivery_date | J1: customer_type | K1: payment_mode | L1: profit | M1: city | N1: Column1 | O1: Column2
A2: ORD100000 | B2: =TEXT(C2,"MMMM") -> March | C2: 45015 | D2: East | E2: 713.49 | F2: Clothing | G2: =E2*10% -> 71.349 | H2: 3 | I2: 45017 | J2: Member | K2: UPI | L2: 114.72 | M2: Pune
A3: ORD100001 | B3: =TEXT(C3,"MMMM") -> August | C3: 45166 | D3: West | E3: 3802.97 | F3: Electronics | G3: =E3*10% -> 380.297 | H3: 4 | I3: 45172 | J3: Regular | K3: Card | L3: 971.41 | M3: Hyderabad
A4: ORD100002 | B4: =TEXT(C4,"MMMM") -> March | C4: 45360 | D4: North | E4: 3588.97 | F4: Home Care | G4: =E4*10% -> 358.897 | H4: 7 | I4: 45366 | J4: Regular | K4: Cash | L4: 769.08 | M4: Bangalore
A5: ORD100003 | B5: =TEXT(C5,"MMMM") -> October | C5: 45578 | D5: East | E5: 1160.86 | F5: Electronics | G5: =E5*10% -> 116.086 | H5: 5 | I5: 45584 | J5: Member | K5: UPI | L5: 71.61 | M5: Pune
A6: ORD100004 | B6: =TEXT(C6,"MMMM") -> April | C6: 45022 | D6: East | E6: 3071.32 | F6: Electronics | G6: =E6*10% -> 307.132 | H6: 7 | I6: 45025 | J6: New | K6: Cash | L6: 621.92 | M6: Bangalore
A7: ORD100005 | B7: =TEXT(C7,"MMMM") -> July | C7: 45108 | D7: West | E7: 2566.18 | F7: Grocery | G7: =E7*10% -> 256.618 | H7: 6 | I7: 45111 | J7: Member | K7: UPI | L7: 578.94 | M7: Mumbai
A8: ORD100006 | B8: =TEXT(C8,"MMMM") -> July | C8: 45119 | D8: North | E8: 398 | F8: Personal Care | G8: =E8*10% -> 39.8 | H8: 4 | I8: 45124 | J8: New | K8: Cash | L8: 110.31 | M8: Mumbai | N8: Sales_By_Region_North | O8: Sales_By_Region_East
A9: ORD100007 | B9: =TEXT(C9,"MMMM") -> May | C9: 45064 | D9: North | E9: 1462.95 | F9: Personal Care | G9: =E9*10% -> 146.295 | H9: 2 | I9: 45066 | J9: Regular | K9: UPI | L9: 91.68 | M9: Bangalore | N9: =SUMIF(Table_1[region],D4,Table_1[sales]) -> 10143913 | O9: =SUMIF(Table_1[region],D2,Table_1[sales]) -> 9518321.9
A10: ORD100008 | B10: =TEXT(C10,"MMMM") -> January | C10: 45296 | D10: East | E10: 4997.47 | F10: Personal Care | G10: =E10*10% -> 499.747 | H10: 6 | I10: 45299 | J10: Regular | K10: Card | L10: 995.78 | M10: Delhi | N10: Sales_By_Region_West | O10: Sales_By_Region_South
A11: ORD100009 | B11: =TEXT(C11,"MMMM") -> August | C11: 45514 | D11: South | E11: 587.72 | F11: Grocery | G11: =E11*10% -> 58.772 | H11: 6 | I11: 45521 | J11: New | K11: Cash | L11: 102.96 | M11: Pune | N11: =SUMIF(Table_1[region],D7,Table_1[sales]) -> 9748863.1 | O11: =SUMIF(Table_1[region],Table_1[[#This Row],[region]],Table_1[sales]) -> 9851779.2
A12: ORD100010 | B12: =TEXT(C12,"MMMM") -> May | C12: 45419 | D12: East | E12: 2581.42 | F12: Clothing | G12: =E12*10% -> 258.142 | H12: 6 | I12: 45420 | J12: Regular | K12: Cash | L12: 542.82 | M12: Bangalore
A13: ORD100011 | B13: =TEXT(C13,"MMMM") -> September | C13: 45171 | D13: East | E13: 4261.74 | F13: Clothing | G13: =E13*10% -> 426.174 | H13: 1 | I13: 45172 | J13: New | K13: UPI | L13: 1028.47 | M13: Pune
A14: ORD100012 | B14: =TEXT(C14,"MMMM") -> February | C14: 45331 | D14: East | E14: 1573.19 | F14: Home Care | G14: =E14*10% -> 157.319 | H14: 6 | I14: 45338 | J14: New | K14: Cash | L14: 131.5 | M14: Bangalore | N14: Region | O14: Order
A15: ORD100013 | B15: =TEXT(C15,"MMMM") -> May | C15: 45074 | D15: East | E15: 1377.47 | F15: Clothing | G15: =E15*10% -> 137.747 | H15: 2 | I15: 45075 | J15: Member | K15: Cash | L15: 255.49 | M15: Delhi | N15: East | O15: =COUNTIF(Table_1[region],Table_1[[#This Row],[Column1]]) -> 3778
A16: ORD100014 | B16: =TEXT(C16,"MMMM") -> January | C16: 45296 | D16: West | E16: 4464.89 | F16: Clothing | G16: =E16*10% -> 446.489 | H16: 5 | I16: 45303 | J16: Regular | K16: UPI | L16: 804.36 | M16: Pune | N16: West | O16: =COUNTIF(Table_1[region],Table_1[[#This Row],[Column1]]) -> 3790
A17: ORD100015 | B17: =TEXT(C17,"MMMM") -> October | C17: 45583 | D17: North | E17: 1593.67 | F17: Personal Care | G17: =E17*10% -> 159.367 | H17: 7 | I17: 45587 | J17: Member | K17: Card | L17: 284.91 | M17: Chennai | N17: South | O17: =COUNTIF(Table_1[region],Table_1[[#This Row],[Column1]]) -> 3853
A18: ORD100016 | B18: =TEXT(C18,"MMMM") -> April | C18: 45042 | D18: West | E18: 3292.32 | F18: Electronics | G18: =E18*10% -> 329.232 | H18: 1 | I18: 45043 | J18: Member | K18: Card | L18: 504.83 | M18: Mumbai | N18: North | O18: =COUNTIF(Table_1[region],Table_1[[#This Row],[Column1]]) -> 3924
A19: ORD100017 | B19: =TEXT(C19,"MMMM") -> October | C19: 45228 | D19: West | E19: 3727.53 | F19: Clothing | G19: =E19*10% -> 372.753 | H19: 5 | I19: 45235 | J19: Regular | K19: Card | L19: 978.07 | M19: Chennai
A20: ORD100018 | B20: =TEXT(C20,"MMMM") -> June | C20: 45448 | D20: West | E20: 3964.23 | F20: Clothing | G20: =E20*10% -> 396.423 | H20: 9 | I20: 45451 | J20: Member | K20: UPI | L20: 260.95 | M20: Bangalore
A21: ORD100019 | B21: =TEXT(C21,"MMMM") -> May | C21: 45047 | D21: East | E21: 4974.32 | F21: Grocery | G21: =E21*10% -> 497.432 | H21: 3 | I21: 45051 | J21: Regular | K21: Card | L21: 727.29 | M21: Delhi
A22: ORD100020 | B22: =TEXT(C22,"MMMM") -> October | C22: 45586 | D22: South | E22: 4035.64 | F22: Home Care | G22: =E22*10% -> 403.564 | H22: 2 | I22: 45593 | J22: Regular | K22: Cash | L22: 798.81 | M22: Delhi | N22: Region | O22: Order
A23: ORD100021 | B23: =TEXT(C23,"MMMM") -> August | C23: 45153 | D23: North | E23: 3319.36 | F23: Grocery | G23: =E23*10% -> 331.936 | H23: 2 | I23: 45159 | J23: Member | K23: Cash | L23: 920.22 | M23: Bangalore | N23: East | O23: =SUMIF(Table_1[region],Table_1[[#This Row],[Column1]],Table_1[sales]) -> 9518321.9
A24: ORD100022 | B24: =TEXT(C24,"MMMM") -> December | C24: 45657 | D24: South | E24: 4487.77 | F24: Personal Care | G24: =E24*10% -> 448.777 | H24: 3 | I24: 45659 | J24: Regular | K24: Card | L24: 931.37 | M24: Pune | N24: West | O24: =SUMIF(Table_1[region],Table_1[[#This Row],[Column1]],Table_1[sales]) -> 9748863.1
A25: ORD100023 | B25: =TEXT(C25,"MMMM") -> March | C25: 45005 | D25: West | E25: 4538.15 | F25: Electronics | G25: =E25*10% -> 453.815 | H25: 1 | I25: 45008 | J25: Regular | K25: Cash | L25: 375.7 | M25: Delhi | N25: South | O25: =SUMIF(Table_1[region],Table_1[[#This Row],[Column1]],Table_1[sales]) -> 9851779.2
A26: ORD100024 | B26: =TEXT(C26,"MMMM") -> December | C26: 45272 | D26: West | E26: 4868.52 | F26: Home Care | G26: =E26*10% -> 486.852 | H26: 2 | I26: 45273 | J26: Regular | K26: Cash | L26: 1072.26 | M26: Mumbai | N26: North | O26: =SUMIF(Table_1[region],Table_1[[#This Row],[Column1]],Table_1[sales]) -> 10143913
A27: ORD100025 | B27: =TEXT(C27,"MMMM") -> May | C27: 45066 | D27: South | E27: 3904.68 | F27: Grocery | G27: =E27*10% -> 390.468 | H27: 6 | I27: 45072 | J27: Regular | K27: Card | L27: 526.66 | M27: Hyderabad | N27: Total Sales | O27: =SUBTOTAL(109,O22:O26) -> 39262878
A28: ORD100026 | B28: =TEXT(C28,"MMMM") -> June | C28: 45462 | D28: South | E28: 1055.14 | F28: Clothing | G28: =E28*10% -> 105.514 | H28: 8 | I28: 45468 | J28: Member | K28: UPI | L28: 207.61 | M28: Chennai
A29: ORD100027 | B29: =TEXT(C29,"MMMM") -> October | C29: 45215 | D29: South | E29: 3578.05 | F29: Clothing | G29: =E29*10% -> 357.805 | H29: 4 | I29: 45217 | J29: New | K29: Card | L29: 689.74 | M29: Mumbai
A30: ORD100028 | B30: =TEXT(C30,"MMMM") -> November | C30: 45255 | D30: West | E30: 468.13 | F30: Home Care | G30: =E30*10% -> 46.813 | H30: 2 | I30: 45261 | J30: Member | K30: UPI | L30: 43.58 | M30: Hyderabad
A31: ORD100029 | B31: =TEXT(C31,"MMMM") -> March | C31: 45356 | D31: West | E31: 1658.02 | F31: Clothing | G31: =E31*10% -> 165.802 | H31: 5 | I31: 45357 | J31: New | K31: Cash | L31: 422.33 | M31: Delhi
A32: ORD100030 | B32: =TEXT(C32,"MMMM") -> April | C32: 45026 | D32: North | E32: 667.46 | F32: Grocery | G32: =E32*10% -> 66.746 | H32: 3 | I32: 45031 | J32: New | K32: Card | L32: 123.49 | M32: Pune
A33: ORD100031 | B33: =TEXT(C33,"MMMM") -> August | C33: 45527 | D33: North | E33: 4754.72 | F33: Grocery | G33: =E33*10% -> 475.472 | H33: 5 | I33: 45531 | J33: New | K33: Cash | L33: 697.03 | M33: Chennai
A34: ORD100032 | B34: =TEXT(C34,"MMMM") -> January | C34: 44933 | D34: West | E34: 1759.9 | F34: Clothing | G34: =E34*10% -> 175.99 | H34: 3 | I34: 44939 | J34: Regular | K34: Cash | L34: 178.58 | M34: Delhi
A35: ORD100033 | B35: =TEXT(C35,"MMMM") -> June | C35: 45097 | D35: South | E35: 3594.76 | F35: Clothing | G35: =E35*10% -> 359.476 | H35: 4 | I35: 45099 | J35: New | K35: UPI | L35: 1002.97 | M35: Delhi
A36: ORD100034 | B36: =TEXT(C36,"MMMM") -> September | C36: 45189 | D36: South | E36: 2899.46 | F36: Personal Care | G36: =E36*10% -> 289.946 | H36: 5 | I36: 45190 | J36: Regular | K36: Cash | L36: 320.43 | M36: Bangalore
A37: ORD100035 | B37: =TEXT(C37,"MMMM") -> January | C37: 45298 | D37: North | E37: 626.81 | F37: Electronics | G37: =E37*10% -> 62.681 | H37: 7 | I37: 45303 | J37: Regular | K37: UPI | L37: 177.84 | M37: Mumbai
A38: ORD100036 | B38: =TEXT(C38,"MMMM") -> June | C38: 45470 | D38: West | E38: 2850.59 | F38: Home Care | G38: =E38*10% -> 285.059 | H38: 2 | I38: 45474 | J38: Regular | K38: Card | L38: 528.38 | M38: Chennai
A39: ORD100037 | B39: =TEXT(C39,"MMMM") -> December | C39: 45651 | D39: North | E39: 3339.02 | F39: Grocery | G39: =E39*10% -> 333.902 | H39: 6 | I39: 45652 | J39: Member | K39: Cash | L39: 586.69 | M39: Hyderabad
... A15346: ORD115344 | B15346: =TEXT(C15346,"MMMM") -> November | C15346: 45248 | D15346: South | E15346: 4984.32 | F15346: Grocery | G15346: =E15346*10% -> 498.432 | H15346: 3 | I15346: 45249 | J15346: New | K15346: Card | L15346: 909.1 | M15346: Bangalore

Sheet Profit Margien and Discount
A1: Profit/sale | B1: Profit_Margin% | C1: Discount
A2: East | B2: =SUMIF(Table_1[region],'Profit Margien and Discount'!A2,Table_1[profit])/SUMIF(Table_1[region],'Profit Margien and Discount'!A2,Table_1[sales]) -> 0.17600559 | C2: =SUMIF(Table_1[region],Table_1[[#This Row],[region]],Table_1[discount]) -> 951832.19
A3: West | B3: =SUMIF(Table_1[region],'Profit Margien and Discount'!A3,Table_1[profit])/SUMIF(Table_1[region],'Profit Margien and Discount'!A3,Table_1[sales]) -> 0.17579507 | C3: =SUMIF(Table_1[region],'Profit Margien and Discount'!A3,Table_1[discount]) -> 974886.31
A4: North | B4: =SUMIF(Table_1[region],'Profit Margien and Discount'!A4,Table_1[profit])/SUMIF(Table_1[region],'Profit Margien and Discount'!A4,Table_1[sales]) -> 0.17439235 | C4: =SUMIF(Table_1[region],'Profit Margien and Discount'!A4,Table_1[discount]) -> 1014391.3
A5: South | B5: =SUMIF(Table_1[region],'Profit Margien and Discount'!A5,Table_1[profit])/SUMIF(Table_1[region],'Profit Margien and Discount'!A5,Table_1[sales]) -> 0.17398268 | C5: =SUMIF(Table_1[region],'Profit Margien and Discount'!A5,Table_1[discount]) -> 985177.92
C6: Total Revenue | D6: =SUM(C2:C5) -> 3926287.8

Sheet Dashboards
E2: D-MART RETAIL BUSINESS DASHBOARD
